XStatic_Angular_UUID-0.0.4.0-py2.7-nspkg.pth
XStatic_Angular_UUID-0.0.4.0.dist-info/METADATA
XStatic_Angular_UUID-0.0.4.0.dist-info/RECORD
XStatic_Angular_UUID-0.0.4.0.dist-info/WHEEL
XStatic_Angular_UUID-0.0.4.0.dist-info/namespace_packages.txt
XStatic_Angular_UUID-0.0.4.0.dist-info/top_level.txt
xstatic/pkg/angular_uuid/__init__.py
xstatic/pkg/angular_uuid/data/angular-uuid.js
