Metadata-Version: 2.1
Name: XStatic-Angular-UUID
Version: 0.0.4.0
Summary: Angular-UUID 0.0.4 (XStatic packaging standard)
Home-page: https://github.com/munkychop/angular-uuid
Maintainer: xinni.ge
Maintainer-email: xinni.ge@ntt.com
License: MIT
Keywords: angular_uuid xstatic
Platform: any
